intake_erddap/__init__.py
intake_erddap/_version.py
intake_erddap/cache.py
intake_erddap/erddap.py
intake_erddap/erddap_cat.py
intake_erddap/utils.py
intake_erddap-0.5.2.dist-info/LICENSE
intake_erddap-0.5.2.dist-info/METADATA
intake_erddap-0.5.2.dist-info/WHEEL
intake_erddap-0.5.2.dist-info/entry_points.txt
intake_erddap-0.5.2.dist-info/top_level.txt
intake_erddap-0.5.2.dist-info/RECORD
