Metadata-Version: 2.1
Name: intake-erddap
Version: 0.5.2
Summary: ERDDAP plugin for Intake
Home-page: https://github.com/axiom-data-science/intake-erddap
Maintainer: Axiom Data Science
Maintainer-email: dev@axds.co
License: BSD
License-File: LICENSE
Requires-Dist: appdirs
Requires-Dist: erddapy
Requires-Dist: intake
Requires-Dist: intake-xarray
Requires-Dist: numpy
Requires-Dist: pandas
Requires-Dist: xarray
